decoder_plus_plus-1.8.6.data/data/share/applications/dpp.desktop
decoder_plus_plus-1.8.6.data/data/share/icons/hicolor/scalable/apps/dpp.png
dpp/__init__.py
dpp/__main__.py
dpp/runner.py
dpp/core/__init__.py
dpp/core/argparse.py
dpp/core/assertions.py
dpp/core/config.py
dpp/core/context.py
dpp/core/decoder_plus_plus.py
dpp/core/exceptions.py
dpp/core/icons.py
dpp/core/listener.py
dpp/core/logger.py
dpp/core/math.py
dpp/core/shortcuts.py
dpp/core/plugin/__init__.py
dpp/core/plugin/builder.py
dpp/core/plugin/loader.py
dpp/core/plugin/manager.py
dpp/core/plugin/config/__init__.py
dpp/core/plugin/config/options/__init__.py
dpp/core/plugin/config/ui/__init__.py
dpp/core/plugin/config/ui/layouts.py
dpp/core/plugin/config/ui/widgets.py
dpp/images/dpp.png
dpp/images/dpp_128.png
dpp/images/dpp_classic.png
dpp/images/dpp_classic_128.png
dpp/images/dpp_modern.png
dpp/images/dpp_modern_128.png
dpp/images/dpp_modern_big.png
dpp/images/dpp_stylized.png
dpp/images/dpp_stylized_128.png
dpp/images/dpp_xmas.png
dpp/images/dpp_xmas_stylized.png
dpp/images/hidden.png
dpp/images/indicator_green.png
dpp/images/indicator_grey.png
dpp/images/indicator_red.png
dpp/images/keyboard.png
dpp/images/keyboard.svg
dpp/plugins/adler32_hasher.py
dpp/plugins/apache_md5_hasher.py
dpp/plugins/base16_decoder.py
dpp/plugins/base16_encoder.py
dpp/plugins/base32_decoder.py
dpp/plugins/base32_encoder.py
dpp/plugins/base45_decoder.py
dpp/plugins/base45_encoder.py
dpp/plugins/base64_decoder.py
dpp/plugins/base64_encoder.py
dpp/plugins/base64_url_decoder.py
dpp/plugins/base64_url_encoder.py
dpp/plugins/bin_int_decoder.py
dpp/plugins/bin_int_encoder.py
dpp/plugins/bin_str_decoder.py
dpp/plugins/bin_str_encoder.py
dpp/plugins/caesar_cipher_script.py
dpp/plugins/clone_script.py
dpp/plugins/crc32_hasher.py
dpp/plugins/css_minify_script.py
dpp/plugins/custom_code.py
dpp/plugins/dec_str_decoder.py
dpp/plugins/dec_str_encoder.py
dpp/plugins/escape_string_script.py
dpp/plugins/extract_urls_script.py
decoder_plus_plus-1.8.6.dist-info/LICENSE
decoder_plus_plus-1.8.6.dist-info/METADATA
decoder_plus_plus-1.8.6.dist-info/WHEEL
decoder_plus_plus-1.8.6.dist-info/entry_points.txt
decoder_plus_plus-1.8.6.dist-info/top_level.txt
decoder_plus_plus-1.8.6.dist-info/RECORD
