Metadata-Version: 2.1
Name: decoder-plus-plus
Version: 1.8.6
Summary: An extensible application for penetration testers and software developers to decode/encode data into various formats.
Home-page: https://github.com/bytebutcher/decoder-plus-plus
Author: bytebutcher
Author-email: thomas.engel.web@gmail.com
License: GPL-3.0
Platform: UNKNOWN
Classifier: Programming Language :: Python :: 3
Classifier: Operating System :: OS Independent
License-File: LICENSE
Requires-Dist: QtAwesome >=1.0.2
Requires-Dist: filemagic >=1.6
Requires-Dist: fuzzywuzzy >=0.18.0
Requires-Dist: hashid >=3.1.4
Requires-Dist: lxml >=4.9.1
Requires-Dist: qtpy >=2.0.0
Requires-Dist: qtpynodeeditor >=0.2.0
Requires-Dist: urlextract >=1.6.0
Provides-Extra: extras
Requires-Dist: PyJWT >=2.8.0 ; extra == 'extras'
Requires-Dist: base45 >=0.4.0 ; extra == 'extras'
Requires-Dist: css-html-js-minify >=2.5.0 ; extra == 'extras'
Requires-Dist: jc >=1.21.0 ; extra == 'extras'
Requires-Dist: jsbeautifier >=1.14.0 ; extra == 'extras'
Requires-Dist: json2xml >=3.19.0 ; extra == 'extras'
Requires-Dist: jsonpath-ng >=1.5.0 ; extra == 'extras'
Requires-Dist: magika >=0.5.0 ; extra == 'extras'
Requires-Dist: passlib >=1.7.0 ; extra == 'extras'
Requires-Dist: pycryptodome >=3.15.0 ; extra == 'extras'
Requires-Dist: validators >=0.20.0 ; extra == 'extras'
Provides-Extra: qt5
Requires-Dist: PyQt5 <5.16 ; extra == 'qt5'
Provides-Extra: qt6
Requires-Dist: PyQt6 <6.3.0 ; extra == 'qt6'
Provides-Extra: test
Requires-Dist: pytest-qt >=4.2.0 ; extra == 'test'
